{
  "animateLoading": true,
  "borderRadius": "{{appsmith.theme.borderRadius.appBorderRadius}}",
  "bottomRow": 39,
  "boxShadow": "none",
  "buttonColor": "{{Update_Association_Color.text}}",
  "buttonVariant": "PRIMARY",
  "disabledWhenInvalid": true,
  "dynamicBindingPathList": [
    {
      "key": "buttonColor"
    },
    {
      "key": "borderRadius"
    }
  ],
  "dynamicPropertyPathList": [
    {
      "key": "onClick"
    },
    {
      "key": "buttonColor"
    }
  ],
  "dynamicTriggerPathList": [
    {
      "key": "onClick"
    }
  ],
  "isDefaultClickDisabled": true,
  "isDisabled": false,
  "isLoading": false,
  "isVisible": true,
  "key": "f4myvxl9e3",
  "leftColumn": 19,
  "minWidth": 120,
  "mobileBottomRow": 37,
  "mobileLeftColumn": 46,
  "mobileRightColumn": 62,
  "mobileTopRow": 33,
  "needsErrorInfo": false,
  "onClick": "{{ ActivityInput.run(() => {\n  showAlert(\"Ticket submitted successfully!\", \"success\");\n}, () => {\n  showAlert(\"Ticket submission failed\", \"error\");\n}); }}",
  "originalBottomRow": 39,
  "originalTopRow": 35,
  "parentId": "4qsna2g42d",
  "placement": "CENTER",
  "recaptchaType": "V3",
  "renderMode": "CANVAS",
  "resetFormOnClick": true,
  "responsiveBehavior": "hug",
  "rightColumn": 60,
  "text": "Submit",
  "topRow": 35,
  "type": "BUTTON_WIDGET",
  "version": 1,
  "widgetId": "e36sn38uc0",
  "widgetName": "Submit"
}