{
  "accentColor": "{{appsmith.theme.colors.primaryColor}}",
  "animateLoading": true,
  "autoFocus": false,
  "borderRadius": "0.375rem",
  "bottomRow": 84,
  "boxShadow": "0 10px 15px -3px rgba(0, 0, 0, 0.1), 0 4px 6px -2px rgba(0, 0, 0, 0.05)",
  "defaultText": "",
  "dynamicBindingPathList": [
    {
      "key": "accentColor"
    },
    {
      "key": "validation"
    }
  ],
  "dynamicHeight": "FIXED",
  "dynamicPropertyPathList": [],
  "dynamicTriggerPathList": [],
  "errorMessage": "Please enter only the LinkedIn handle (e.g., in/username or company/username). Do not include the full URL or \"linkedin.com\".",
  "iconAlign": "left",
  "iconName": "link",
  "inputType": "TEXT",
  "isDisabled": false,
  "isLoading": false,
  "isRequired": false,
  "isVisible": true,
  "key": "ib9d7h44x1",
  "label": "LinkedIn",
  "labelAlignment": "left",
  "labelPosition": "Top",
  "labelStyle": "",
  "labelTextSize": "0.875rem",
  "labelWidth": 5,
  "leftColumn": 41,
  "maxDynamicHeight": 9000,
  "minDynamicHeight": 4,
  "minWidth": 450,
  "mobileBottomRow": 14,
  "mobileLeftColumn": 13,
  "mobileRightColumn": 33,
  "mobileTopRow": 7,
  "needsErrorInfo": false,
  "originalBottomRow": 84,
  "originalTopRow": 77,
  "parentColumnSpace": 6.55419921875,
  "parentId": "z4ubp6jcef",
  "parentRowSpace": 10,
  "renderMode": "CANVAS",
  "resetOnSubmit": true,
  "responsiveBehavior": "fill",
  "rightColumn": 60,
  "showStepArrows": false,
  "topRow": 77,
  "type": "INPUT_WIDGET_V2",
  "validation": "{{ /^(?!.*linkedin\\.com)(?:in|company)\\/[a-zA-Z0-9-]{3,100}$/.test(New_Association_Linkedin.text) }}",
  "version": 2,
  "widgetId": "gjok0z2z07",
  "widgetName": "New_Association_Linkedin"
}